envisage/__init__.py
envisage/api.py
envisage/application.py
envisage/application_event.py
envisage/composite_plugin_manager.py
envisage/core_plugin.py
envisage/egg_basket_plugin_manager.py
envisage/egg_plugin_manager.py
envisage/egg_utils.py
envisage/extension_point.py
envisage/extension_point_binding.py
envisage/extension_point_changed_event.py
envisage/extension_provider.py
envisage/extension_registry.py
envisage/i_application.py
envisage/i_extension_point.py
envisage/i_extension_point_user.py
envisage/i_extension_provider.py
envisage/i_extension_registry.py
envisage/i_import_manager.py
envisage/i_plugin.py
envisage/i_plugin_activator.py
envisage/i_plugin_manager.py
envisage/i_provider_extension_registry.py
envisage/i_service_registry.py
envisage/i_service_user.py
envisage/ids.py
envisage/import_manager.py
envisage/package_plugin_manager.py
envisage/plugin.py
envisage/plugin_activator.py
envisage/plugin_event.py
envisage/plugin_extension_registry.py
envisage/plugin_manager.py
envisage/provider_extension_registry.py
envisage/service.py
envisage/service_offer.py
envisage/service_registry.py
envisage/unknown_extension.py
envisage/unknown_extension_point.py
envisage/examples/__init__.py
envisage/examples/_demo.py
envisage/examples/_etsdemo_info.py
envisage/examples/demo/GUI_Application/traitsui_gui_app.py
envisage/examples/demo/Hello_World/hello_world.py
envisage/examples/demo/MOTD/run.py
envisage/examples/demo/MOTD/acme/__init__.py
envisage/examples/demo/MOTD/acme/motd/__init__.py
envisage/examples/demo/MOTD/acme/motd/api.py
envisage/examples/demo/MOTD/acme/motd/i_message.py
envisage/examples/demo/MOTD/acme/motd/i_motd.py
envisage/examples/demo/MOTD/acme/motd/message.py
envisage/examples/demo/MOTD/acme/motd/motd.py
envisage/examples/demo/MOTD/acme/motd/motd_plugin.py
envisage/examples/demo/MOTD/acme/motd/software_quotes/__init__.py
envisage/examples/demo/MOTD/acme/motd/software_quotes/messages.py
envisage-7.0.3.dist-info/LICENSE.txt
envisage-7.0.3.dist-info/METADATA
envisage-7.0.3.dist-info/WHEEL
envisage-7.0.3.dist-info/entry_points.txt
envisage-7.0.3.dist-info/top_level.txt
envisage-7.0.3.dist-info/RECORD
