Metadata-Version: 2.1
Name: envisage
Version: 7.0.3
Summary: Extensible application framework
Author-email: Enthought <info@enthought.com>
License: This software is OSI Certified Open Source Software.
Project-URL: documentation, https://docs.enthought.com/envisage/
Project-URL: repository, https://github.com/enthought/envisage
Project-URL: issues, https://github.com/enthought/envisage/issues
Keywords: extensible,plugin,application,framework
Classifier: Development Status :: 5 - Production/Stable
Classifier: Intended Audience :: Developers
Classifier: Intended Audience :: Science/Research
Classifier: License :: OSI Approved :: BSD License
Classifier: Operating System :: MacOS :: MacOS X
Classifier: Operating System :: Microsoft :: Windows
Classifier: Operating System :: POSIX :: Linux
Classifier: Programming Language :: Python
Classifier: Programming Language :: Python :: 3
Classifier: Programming Language :: Python :: Implementation :: CPython
Classifier: Topic :: Scientific/Engineering
Classifier: Topic :: Software Development
Classifier: Topic :: Software Development :: Libraries
Classifier: Topic :: Software Development :: User Interfaces
Requires-Python: >=3.7
License-File: LICENSE.txt
